README.md
setup.py
servusnumre/__init__.py
servusnumre.egg-info/PKG-INFO
servusnumre.egg-info/SOURCES.txt
servusnumre.egg-info/dependency_links.txt
servusnumre.egg-info/top_level.txt