Metadata-Version: 2.1
Name: servusnumre
Version: 0.1
Summary: Python3 module with regex patterns related to numbers.
Home-page: https://github.com/carlosplanchon/servusnumre
Author: Carlos A. Planchón
Author-email: bubbledoloresuruguay2@gmail.com
License: GPL3
Download-URL: https://github.com/carlosplanchon/servusnumre/archive/v0.1.tar.gz
Keywords: regex,patterns,numbers
Platform: UNKNOWN
Classifier: Intended Audience :: Developers
Classifier: Topic :: Software Development :: Build Tools
Classifier: License :: OSI Approved :: GNU General Public License v3 (GPLv3)
Classifier: Programming Language :: Python :: 3
Classifier: Programming Language :: Python :: 3.4
Classifier: Programming Language :: Python :: 3.5
Classifier: Programming Language :: Python :: 3.6
Classifier: Programming Language :: Python :: 3.7
